pyquicktools/__init__.py
pyquicktools/__main__.py
pyquicktools/debug_print.py
pyquicktools/doctor.py
pyquicktools/http_retry.py
pyquicktools/safe_json.py
pyquicktools-0.1.0.dist-info/licenses/LICENSE
pyquicktools-0.1.0.dist-info/METADATA
pyquicktools-0.1.0.dist-info/WHEEL
pyquicktools-0.1.0.dist-info/top_level.txt
pyquicktools-0.1.0.dist-info/RECORD
