Metadata-Version: 2.4
Name: pyquicktools
Version: 0.1.0
Summary: Smart Python utilities for HTTP retries, logging control, async retries, and diagnostics CLI
Author-email: Suhani Garg <suhanigarg59@gmail.com>
License: MIT
Project-URL: Homepage, https://github.com/Suhani1234-5/pyquicktools
Project-URL: Repository, https://github.com/Suhani1234-5/pyquicktools
Project-URL: Issues, https://github.com/Suhani1234-5/pyquicktools/issues
Keywords: python,http,retry,requests,cli,utilities,logging,devtools
Classifier: Programming Language :: Python :: 3
Classifier: Programming Language :: Python :: 3.8
Classifier: Programming Language :: Python :: 3.9
Classifier: Programming Language :: Python :: 3.10
Classifier: Programming Language :: Python :: 3.11
Classifier: Programming Language :: Python :: 3.12
Classifier: Operating System :: OS Independent
Classifier: License :: OSI Approved :: MIT License
Requires-Python: >=3.8
License-File: LICENSE
Requires-Dist: requests>=2.28
Provides-Extra: async
Requires-Dist: aiohttp>=3.8; extra == "async"
Dynamic: license-file
